csgo_handler/__init__.py
csgo_handler-1.1.2.data/scripts/csgo-handler
csgo_handler-1.1.2.dist-info/LICENSE.md
csgo_handler-1.1.2.dist-info/METADATA
csgo_handler-1.1.2.dist-info/WHEEL
csgo_handler-1.1.2.dist-info/top_level.txt
csgo_handler-1.1.2.dist-info/RECORD
