Metadata-Version: 2.1
Name: csgo-handler
Version: 1.1.2
Summary: Daemon to run a program when CS:GO starts and stops
Home-page: https://gitlab.com/aw1cks/csgo_handler
Author: Alex Wicks
Author-email: alex@awicks.io
License: AGPLv3
Download-URL: https://gitlab.com/aw1cks/csgo_handler
Keywords: csgo
Platform: linux
Classifier: Development Status :: 3 - Alpha
Classifier: Intended Audience :: End Users/Desktop
Classifier: License :: OSI Approved :: GNU Affero General Public License v3
Classifier: Operating System :: POSIX :: Linux
Classifier: Programming Language :: Python :: 3 :: Only
Classifier: Programming Language :: Python :: 3.6
Classifier: Programming Language :: Python :: 3.7
Classifier: Programming Language :: Python :: 3.8
Classifier: Programming Language :: Python :: 3.9
Classifier: Programming Language :: Python :: 3.10
Classifier: Topic :: Communications :: Chat
Requires-Python: >=3.6
License-File: LICENSE.md
Requires-Dist: python-daemon
Requires-Dist: inotify
